CHANGES.txt
LICENSE.txt
MANIFEST.in
README.txt
setup.py
js/__init__.py
js.jquery_gritter.egg-info/PKG-INFO
js.jquery_gritter.egg-info/SOURCES.txt
js.jquery_gritter.egg-info/dependency_links.txt
js.jquery_gritter.egg-info/entry_points.txt
js.jquery_gritter.egg-info/namespace_packages.txt
js.jquery_gritter.egg-info/not-zip-safe
js.jquery_gritter.egg-info/requires.txt
js.jquery_gritter.egg-info/top_level.txt
js/jquery_gritter/__init__.py
js/jquery_gritter/test_jquery-gritter.txt
js/jquery_gritter/resources/.DS_Store
js/jquery_gritter/resources/css/jquery.gritter.css
js/jquery_gritter/resources/css/jquery.gritter.min.css
js/jquery_gritter/resources/images/gritter-light.png
js/jquery_gritter/resources/images/gritter-long.png
js/jquery_gritter/resources/images/gritter.png
js/jquery_gritter/resources/images/ie-spacer.gif
js/jquery_gritter/resources/images/trees.jpg
js/jquery_gritter/resources/js/jquery.gritter.js
js/jquery_gritter/resources/js/jquery.gritter.min.js