Metadata-Version: 1.0
Name: js.jquery-gritter
Version: 1.7.4
Summary: Fanstatic packaging of Gritter for jQuery (jquery.gritter.js)
Home-page: https://bitbucket.org/s_nikolai/js.jquery_gritter
Author: Nikolai Sevostjanov
Author-email: nikolai.sevostjanov@gmail.com
License: BSD
Platform: UNKNOWN
